Metadata-Version: 2.1
Name: containedenv
Version: 0.0.3
Summary: Helper scripts for writing configuration files based on environment variables
Home-page: UNKNOWN
Author: Drew Stinnett
Author-email: drew@drewlink.com
License: MIT
Keywords: container docker
Platform: UNKNOWN
